medium_sdk_python/.git
medium_sdk_python/.gitignore
medium_sdk_python/.travis.yml
medium_sdk_python/LICENSE.TXT
medium_sdk_python/MANIFEST
medium_sdk_python/README.md
medium_sdk_python/medium/__init__.py
medium_sdk_python/requirements.txt
medium_sdk_python/setup.cfg
medium_sdk_python/setup.py
medium_sdk_python/tests/requirements.txt
medium_sdk_python/tests/test.png
medium_sdk_python/tests/test.py
notion2medium/__init__.py
notion2medium/__main__.py
notion2medium/clients/medium.py
notion2medium/clients/notion_client.py
notion2medium/console/__init__.py
notion2medium/console/application.py
notion2medium/console/commands/__init__.py
notion2medium/console/commands/command.py
notion2medium/console/commands/publish.py
notion2medium/console/commands/select.py
notion2medium/exceptions/__init__.py
notion2medium-1.0.1.dist-info/LICENSE
notion2medium-1.0.1.dist-info/METADATA
notion2medium-1.0.1.dist-info/WHEEL
notion2medium-1.0.1.dist-info/entry_points.txt
notion2medium-1.0.1.dist-info/RECORD
